MANIFEST.in
README.rst
setup.py
django_partitions.egg-info/PKG-INFO
django_partitions.egg-info/SOURCES.txt
django_partitions.egg-info/dependency_links.txt
django_partitions.egg-info/not-zip-safe
django_partitions.egg-info/top_level.txt
partitions/__init__.py
partitions/models.py
partitions/registry.py
partitions/utils.py
partitions/templatetags/__init__.py
partitions/templatetags/partitions_tags.py