Metadata-Version: 1.0
Name: django-partitions
Version: 0.1
Summary: an app for partitions querysets based on indexed Q expressions in settings
Home-page: http://github.com/eldarion/django-partitions
Author: Eldarion
Author-email: developers@eldarion.com
License: BSD
Platform: UNKNOWN
Classifier: Development Status :: 3 - Alpha
Classifier: Environment :: Web Environment
Classifier: Intended Audience :: Developers
Classifier: License :: OSI Approved :: BSD License
Classifier: Operating System :: OS Independent
Classifier: Programming Language :: Python
Classifier: Framework :: Django
